nepc/__init__.py
nepc/__version__.py
nepc/curate/__init__.py
nepc/curate/curate.py
nepc/mysql/build.py
nepc/mysql/defaults
nepc/nepc.py
nepc/util/__init__.py
nepc/util/config.py
nepc/util/parser.py
nepc/util/scraper.py
nepc/util/util.py
nepc-2023.9.22.dist-info/LICENSE
nepc-2023.9.22.dist-info/WHEEL
nepc-2023.9.22.dist-info/METADATA
nepc-2023.9.22.dist-info/RECORD
