Metadata-Version: 2.1
Name: nepc
Version: 2023.9.22
Summary: Build, access, and explore a NEPC database.
License: CCO 1.0 Universal
Author: Paul Adamson
Author-email: paul@seekingeta.ai
Requires-Python: >=3.9,<4.0.0
Classifier: License :: Other/Proprietary License
Classifier: Programming Language :: Python :: 3
Classifier: Programming Language :: Python :: 3.9
Classifier: Programming Language :: Python :: 3.10
Classifier: Programming Language :: Python :: 3.11
Requires-Dist: ipython (>=7.3.0,<8.0.0)
Requires-Dist: ipython_genutils (>=0.2.0,<0.3.0)
Requires-Dist: jupyter (>=1.0.0,<2.0.0)
Requires-Dist: jupyter-client (>=8.3.1,<9.0.0)
Requires-Dist: matplotlib (>=3.8.0,<4.0.0)
Requires-Dist: mysql-connector-python (>=8.0.17,<9.0.0)
Requires-Dist: numpy (>=1.16.2,<2.0.0)
Requires-Dist: pandas (>=2.1.0,<3.0.0)
